python_telegram_logging/__init__.py
python_telegram_logging/exceptions.py
python_telegram_logging/rate_limiting.py
python_telegram_logging/schemes.py
python_telegram_logging/handlers/__init__.py
python_telegram_logging/handlers/async_.py
python_telegram_logging/handlers/base_queue.py
python_telegram_logging/handlers/base_telegram.py
python_telegram_logging/handlers/queue.py
python_telegram_logging/handlers/sync.py
python_telegram_logging-0.0.2.dist-info/METADATA
python_telegram_logging-0.0.2.dist-info/WHEEL
python_telegram_logging-0.0.2.dist-info/licenses/LICENSE
python_telegram_logging-0.0.2.dist-info/RECORD
