Metadata-Version: 2.4
Name: python-telegram-logging
Version: 0.0.2
Summary: A Python logging handler that sends logs to Telegram
Project-URL: GitHub, https://github.com/alcibiadescleinias/python-telegram-logging/
Author-email: Ivan Cheprasov <my.phd.memory@gmail.com>
License: MIT License
License-File: LICENSE
Keywords: aiohttp,handler,logging,requests,telegram
Classifier: Development Status :: 4 - Beta
Classifier: Intended Audience :: Developers
Classifier: License :: OSI Approved :: MIT License
Classifier: Programming Language :: Python :: 3
Classifier: Programming Language :: Python :: 3.8
Classifier: Programming Language :: Python :: 3.9
Classifier: Programming Language :: Python :: 3.10
Classifier: Programming Language :: Python :: 3.11
Classifier: Programming Language :: Python :: 3.12
Classifier: Topic :: System :: Logging
Requires-Python: >=3.8
Requires-Dist: aiohttp>=3.8.6
Requires-Dist: requests>=2.31.0
Provides-Extra: dev
Requires-Dist: autoflake==2.1.1; extra == 'dev'
Requires-Dist: black>=23.0.0; extra == 'dev'
Requires-Dist: flake8>=6.1.0; extra == 'dev'
Requires-Dist: isort>=5.12.0; extra == 'dev'
Requires-Dist: mypy>=1.7.0; extra == 'dev'
Requires-Dist: pylint>=3.0.0; extra == 'dev'
Requires-Dist: pytest-asyncio>=0.21.0; extra == 'dev'
Requires-Dist: pytest-cov>=4.1.0; extra == 'dev'
Requires-Dist: pytest>=7.4.0; extra == 'dev'
